lib/__init__.py
lib/kernel_classes.py
crunch_kernel-0.0.2.dist-info/METADATA
crunch_kernel-0.0.2.dist-info/WHEEL
crunch_kernel-0.0.2.dist-info/top_level.txt
crunch_kernel-0.0.2.dist-info/RECORD
