Metadata-Version: 2.1
Name: crunch-kernel
Version: 0.0.2
Summary: Kernel connecting functions
Author: Mukund Chourey
Author-email: <mukund@crunchit.ai>
Keywords: python,crunch,crunchit,kernel
Classifier: Development Status :: 1 - Planning
Classifier: Intended Audience :: Developers
Classifier: Programming Language :: Python :: 3
Classifier: Operating System :: Unix
Classifier: Operating System :: MacOS :: MacOS X
Classifier: Operating System :: Microsoft :: Windows
Requires-Dist: altair
Requires-Dist: vegafusion[embed]
Requires-Dist: snowflake-sqlalchemy
Requires-Dist: google.cloud
Requires-Dist: db-dtypes
